nimbus_postoffice/__init__.py
nimbus_postoffice/backends.py
nimbus_postoffice/utils.py
nimbus_postoffice/migrations/__init__.py
nimbus_postoffice-0.1.0.dist-info/DESCRIPTION.rst
nimbus_postoffice-0.1.0.dist-info/LICENSE.txt
nimbus_postoffice-0.1.0.dist-info/METADATA
nimbus_postoffice-0.1.0.dist-info/RECORD
nimbus_postoffice-0.1.0.dist-info/WHEEL
nimbus_postoffice-0.1.0.dist-info/metadata.json
nimbus_postoffice-0.1.0.dist-info/top_level.txt
